setup.cfg
setup.py
tw/__init__.py
tw/fusioncharts/__init__.py
tw/fusioncharts/elements.py
tw/fusioncharts/meta.py
tw/fusioncharts/release.py
tw/fusioncharts/samples.py
tw/fusioncharts/widgets.py
tw/fusioncharts/templates/__init__.py
tw/fusioncharts/templates/fusioncharts.mak
tw/fusioncharts/templates/single_series.mak
tw/widgets/__init__.py
twFusionCharts.egg-info/PKG-INFO
twFusionCharts.egg-info/SOURCES.txt
twFusionCharts.egg-info/dependency_links.txt
twFusionCharts.egg-info/entry_points.txt
twFusionCharts.egg-info/namespace_packages.txt
twFusionCharts.egg-info/not-zip-safe
twFusionCharts.egg-info/paster_plugins.txt
twFusionCharts.egg-info/requires.txt
twFusionCharts.egg-info/top_level.txt