Metadata-Version: 1.0
Name: twFusionCharts
Version: 0.1a1dev
Summary: Widgets for FusionChartsFree(http://www.fusioncharts.com/free/) based on TGFusionCharts
Home-page: UNKNOWN
Author: Tiago Cordeiro Marques
Author-email: tiago.marques.mail@gmail.com
License: MIT
Keywords: toscawidgets.widgets
Platform: UNKNOWN
Classifier: Development Status :: 3 - Alpha
Classifier: Environment :: Web Environment
Classifier: Environment :: Web Environment :: ToscaWidgets
Classifier: Topic :: Software Development :: Libraries :: Python Modules
Classifier: Topic :: Software Development :: Widget Sets
Classifier: Intended Audience :: Developers
Classifier: Operating System :: OS Independent
Classifier: Programming Language :: Python
